etnn/__init__.py
etnn/combinatorial_data.py
etnn/combinatorial_data.utf8.py
etnn/invariants.py
etnn/layers.py
etnn/lifter.py
etnn/model.py
etnn/utils.py
etnn/geospatial/__init__.py
etnn/geospatial/pm25cc.py
etnn/geospatial/pm25cc_backup_20251015_103828.py
etnn/geospatial/transforms.py
etnn/qm9/__init__.py
etnn/qm9/qm9cc.py
etnn/qm9/lifts/__init__.py
etnn/qm9/lifts/atom.py
etnn/qm9/lifts/bond.py
etnn/qm9/lifts/clique.py
etnn/qm9/lifts/common.py
etnn/qm9/lifts/functional_group.py
etnn/qm9/lifts/molecule.py
etnn/qm9/lifts/registry.py
etnn/qm9/lifts/ring.py
etnn/qm9/lifts/rips_vietoris_complex.py
etnn-0.1.4.dist-info/licenses/LICENSE
etnn-0.1.4.dist-info/METADATA
etnn-0.1.4.dist-info/WHEEL
etnn-0.1.4.dist-info/top_level.txt
etnn-0.1.4.dist-info/RECORD
