Metadata-Version: 2.4
Name: etnn
Version: 0.1.4
Summary: E(n)-Equivariant Topological Neural Networks
Author: ETNN Authors
License: MIT License
Project-URL: Homepage, https://github.com/NSAPH-Projects/topological-equivariant-networks
Project-URL: Repository, https://github.com/NSAPH-Projects/topological-equivariant-networks
Requires-Python: >=3.9
License-File: LICENSE
Requires-Dist: torch>=2.0
Requires-Dist: torch_geometric>=2.5
Requires-Dist: numpy>=1.22
Requires-Dist: scipy>=1.8
Requires-Dist: numba>=0.55
Requires-Dist: toponetx>=0.2.0
Provides-Extra: geo
Requires-Dist: pandas>=1.4; extra == "geo"
Requires-Dist: networkx>=3.1; extra == "geo"
Requires-Dist: matplotlib>=3.7; extra == "geo"
Dynamic: license-file
